pygraphy/__init__.py
pygraphy/context.py
pygraphy/encoder.py
pygraphy/exceptions.py
pygraphy/introspection.py
pygraphy/utils.py
pygraphy/view.py
pygraphy/static/playground.html
pygraphy/types/__init__.py
pygraphy/types/base.py
pygraphy/types/enum.py
pygraphy/types/field.py
pygraphy/types/input.py
pygraphy/types/interface.py
pygraphy/types/object.py
pygraphy/types/schema.py
pygraphy/types/union.py
pygraphy-0.2.5.dist-info/LICENSE
pygraphy-0.2.5.dist-info/METADATA
pygraphy-0.2.5.dist-info/WHEEL
pygraphy-0.2.5.dist-info/top_level.txt
pygraphy-0.2.5.dist-info/RECORD
