Metadata-Version: 2.1
Name: pygraphy
Version: 0.2.5
Summary: A modern pythonic implementation of GraphQL.
Home-page: https://github.com/ethe/pygraphy
Author: Tzu-sing Gwo
Author-email: zi-xing.guo@ubisoft.com
License: MIT
Keywords: python graphql
Platform: UNKNOWN
Classifier: Topic :: Software Development
Classifier: Development Status :: 1 - Planning
Classifier: Intended Audience :: Developers
Classifier: License :: OSI Approved :: MIT License
Classifier: Programming Language :: Python :: 3
Classifier: Programming Language :: Python :: 3.7
Classifier: Programming Language :: Python :: 3.8
Classifier: Programming Language :: Python :: Implementation :: CPython
Classifier: Programming Language :: Python :: Implementation :: PyPy
Requires-Python: >=3.7,<4
Requires-Dist: GraphQL-core-next (<1.2.0,>=1.1.0)
Provides-Extra: dev
Requires-Dist: flake8 (>=3.7.7) ; extra == 'dev'
Requires-Dist: pytest (>=5.0.0) ; extra == 'dev'
Provides-Extra: web
Requires-Dist: starlette (<0.13.0,>=0.12.1) ; extra == 'web'
